[
    {
        "cardId": "base_fire_huo",
        "synthesizeCard": "base_fire_huo",
        "resultResName": "UI/Card/combine_fire_yan",
        "isActive": true
    },
    {
        "cardId": "base_fire_huo",
        "synthesizeCard": "radical_none_xi",
        "resultResName": "UI/Card/combine_fire_zhuo",
        "isActive": true
    },
    {
        "cardId": "base_fire_huo",
        "synthesizeCard": "radical_none_ke",
        "resultResName": "UI/Card/combine_fire_ke",
        "isActive": true
    },
    {
        "cardId": "base_fire_huo",
        "synthesizeCard": "combine_fire_yan3",
        "resultResName": "UI/Card/combine_fire_yi",
        "isActive": true
    },
    {
        "cardId": "base_fire_huo",
        "synthesizeCard": "combine_wood_lin",
        "resultResName": "UI/Card/combine_fire_fen",
        "isActive": true
    },
    {
        "cardId": "base_water_shui",
        "synthesizeCard": "base_water_shui",
        "resultResName": "UI/Card/combine_water_zhui",
        "isActive": true
    },
    {
        "cardId": "base_water_shui",
        "synthesizeCard": "combine_water_zhui",
        "resultResName": "UI/Card/combine_water_miao",
        "isActive": true
    },
    {
        "cardId": "base_water_shui",
        "synthesizeCard": "base_wood_mu",
        "resultResName": "UI/Card/combine_wood_watermu",
        "isActive": true
    },
    {
        "cardId": "base_water_shui",
        "synthesizeCard": "radical_none_xi",
        "resultResName": "UI/Card/combine_water_xi",
        "isActive": true
    },
    {
        "cardId": "base_water_shui",
        "synthesizeCard": "radical_none_ke",
        "resultResName": "UI/Card/combine_water_he",
        "isActive": true
    },
    {
        "cardId": "base_water_shui",
        "synthesizeCard": "radical_none_pi",
        "resultResName": "UI/Card/combine_water_bo",
        "isActive": true
    },
    {
        "cardId": "base_earth_tu",
        "synthesizeCard": "base_earth_tu",
        "resultResName": "UI/Card/combine_earth_gui",
        "isActive": true
    },
    {
        "cardId": "base_earth_tu",
        "synthesizeCard": "radical_none_ke",
        "resultResName": "UI/Card/combine_earth_ke",
        "isActive": true
    },
    {
        "cardId": "base_earth_tu",
        "synthesizeCard": "radical_none_pi",
        "resultResName": "UI/Card/combine_earth_po",
        "isActive": true
    },
    {
        "cardId": "base_earth_tu",
        "synthesizeCard": "radical_none_ye",
        "resultResName": "UI/Card/combine_earth_di",
        "isActive": true
    },
    {
        "cardId": "base_wood_mu",
        "synthesizeCard": "base_wood_mu",
        "resultResName": "UI/Card/combine_wood_lin",
        "isActive": true
    },
    {
        "cardId": "base_wood_mu",
        "synthesizeCard": "base_water_shui",
        "resultResName": "UI/Card/combine_wood_mu",
        "isActive": true
    },
    {
        "cardId": "base_wood_mu",
        "synthesizeCard": "combine_wood_lin",
        "resultResName": "UI/Card/combine_wood_sen",
        "isActive": true
    },
    {
        "cardId": "combine_fire_yan",
        "synthesizeCard": "base_fire_huo",
        "resultResName": "UI/Card/combine_fire_yan3",
        "isActive": true
    },
    {
        "cardId": "combine_fire_yan",
        "synthesizeCard": "combine_fire_yan",
        "resultResName": "UI/Card/combine_fire_yi",
        "isActive": true
    },
    {
        "cardId": "combine_fire_yan3",
        "synthesizeCard": "base_fire_huo",
        "resultResName": "UI/Card/combine_fire_yi",
        "isActive": true
    },
    {
        "cardId": "combine_water_zhui",
        "synthesizeCard": "base_water_shui",
        "resultResName": "UI/Card/combine_water_miao",
        "isActive": true
    },
     {
        "cardId": "combine_earth_gui",
        "synthesizeCard": "base_earth_tu",
        "resultResName": "UI/Card/combine_earth_yao",
        "isActive": true
    },
    {
        "cardId": "combine_wood_lin",
        "synthesizeCard": "base_wood_mu",
        "resultResName": "UI/Card/combine_wood_sen",
        "isActive": true
    }
]